pypeflow/__init__.py
pypeflow-0.0.1.dist-info/LICENSE
pypeflow-0.0.1.dist-info/METADATA
pypeflow-0.0.1.dist-info/WHEEL
pypeflow-0.0.1.dist-info/top_level.txt
pypeflow-0.0.1.dist-info/RECORD
